LICENSE.txt
MANIFEST.in
Pipfile
Pipfile.lock
README.md
pyproject.toml
setup.py
version
djgraphql/__init__.py
djgraphql/apps.py
djgraphql/defaults.py
djgraphql/schema.py
djgraphql/settings.py
djgraphql/urls.py
djgraphql.egg-info/PKG-INFO
djgraphql.egg-info/SOURCES.txt
djgraphql.egg-info/dependency_links.txt
djgraphql.egg-info/requires.txt
djgraphql.egg-info/top_level.txt
djgraphql/test/__init__.py
djgraphql/test/test_routers.py
djgraphql/test/test_schema_generation.py
djgraphql/utils/__init__.py
djgraphql/utils/resolver.py
djgraphql/utils/routes.py